autoschema/__init__.py
autoschema/py.typed
autoschema-1.0.0a0.dist-info/LICENSE
autoschema-1.0.0a0.dist-info/METADATA
autoschema-1.0.0a0.dist-info/WHEEL
autoschema-1.0.0a0.dist-info/top_level.txt
autoschema-1.0.0a0.dist-info/RECORD
